userconf/__init__.py
userconf/files.py
userconf/settings.py
userconf/validation.py
fhuserconf-0.5.12.dist-info/METADATA
fhuserconf-0.5.12.dist-info/WHEEL
fhuserconf-0.5.12.dist-info/RECORD
